fraud_detection/__init__.py
fraud_detection/api.py
fraud_detection/data_processing.py
fraud_detection/model.py
fraud_detection/predict.py
fraud_detection-0.2.dist-info/LICENSE
fraud_detection-0.2.dist-info/METADATA
fraud_detection-0.2.dist-info/WHEEL
fraud_detection-0.2.dist-info/top_level.txt
fraud_detection-0.2.dist-info/RECORD
