Metadata-Version: 2.1
Name: fraud-detection
Version: 0.2
Summary: AI phát hiện gian lận kế toán
Home-page: https://github.com/Trantamming/accounting_fraud_detection
Author: Trần Minh Tâm
Author-email: tam.ming.zhan@gmail.com
License: UNKNOWN
Platform: UNKNOWN
Classifier: Programming Language :: Python :: 3
Classifier: License :: OSI Approved :: MIT License
Classifier: Operating System :: OS Independent
Requires-Python: >=3.7
License-File: LICENSE
Requires-Dist: pandas
Requires-Dist: scikit-learn
Requires-Dist: joblib
